Metadata-Version: 2.1
Name: KurtGroup
Version: 1.1.11
Summary: A package containing scripts and programs developed and used in Professor Kurt V. Mikkelsens group at the University of Copenhagen.
Home-page: UNKNOWN
Author: Theo Juncker von Buchwald
Author-email: fnc970@alumni.ku.dk
License: LICENCSE
Platform: UNKNOWN
Requires-Python: >=3.6
